httpcarousel/__init__.py
httpcarousel/static/refresh.js
httpcarousel/static/style.css
httpcarousel/templates/carousel.js.j2
httpcarousel/templates/index.html.j2
httpcarousel-1.0.3.dist-info/LICENSE
httpcarousel-1.0.3.dist-info/METADATA
httpcarousel-1.0.3.dist-info/WHEEL
httpcarousel-1.0.3.dist-info/entry_points.txt
httpcarousel-1.0.3.dist-info/RECORD
