Metadata-Version: 2.1
Name: httpcarousel
Version: 1.0.3
Summary: Simple HTTP Server to serve a directory of images which frequently rotate
License: MIT
Author: Chris Pressland
Author-email: mail@cpressland.io
Requires-Python: >=3.9,<4.0
Classifier: License :: OSI Approved :: MIT License
Classifier: Programming Language :: Python :: 3
Classifier: Programming Language :: Python :: 3.9
Classifier: Programming Language :: Python :: 3.10
Classifier: Programming Language :: Python :: 3.11
Classifier: Programming Language :: Python :: 3.12
Requires-Dist: fastapi (>=0.109.0,<0.110.0)
Requires-Dist: jinja2 (>=3.1.3,<4.0.0)
Requires-Dist: pydantic-settings (>=2.1.0,<3.0.0)
Requires-Dist: uvicorn (>=0.26.0,<0.27.0)
